odoo/addons/l10n_et_hr_employee_wizard/README.rst
odoo/addons/l10n_et_hr_employee_wizard/__init__.py
odoo/addons/l10n_et_hr_employee_wizard/__manifest__.py
odoo/addons/l10n_et_hr_employee_wizard/models/__init__.py
odoo/addons/l10n_et_hr_employee_wizard/models/hr_applicant.py
odoo/addons/l10n_et_hr_employee_wizard/readme/CREDITS.rst
odoo/addons/l10n_et_hr_employee_wizard/readme/DESCRIPTION.rst
odoo/addons/l10n_et_hr_employee_wizard/static/description/icon.png
odoo/addons/l10n_et_hr_employee_wizard/static/description/index.html
odoo/addons/l10n_et_hr_employee_wizard/tests/__init__.py
odoo/addons/l10n_et_hr_employee_wizard/tests/test_hr_employee_wizard.py
odoo/addons/l10n_et_hr_employee_wizard/views/hr_recruitment_view.xml
odoo/addons/l10n_et_hr_employee_wizard/wizard/__init__.py
odoo/addons/l10n_et_hr_employee_wizard/wizard/hr_employee_wizard_new.py
odoo/addons/l10n_et_hr_employee_wizard/wizard/hr_employee_wizard_views.xml
odoo14_addon_l10n_et_hr_employee_wizard-14.0.1.0.1.dev1.dist-info/METADATA
odoo14_addon_l10n_et_hr_employee_wizard-14.0.1.0.1.dev1.dist-info/WHEEL
odoo14_addon_l10n_et_hr_employee_wizard-14.0.1.0.1.dev1.dist-info/top_level.txt
odoo14_addon_l10n_et_hr_employee_wizard-14.0.1.0.1.dev1.dist-info/RECORD
