Metadata-Version: 2.1
Name: odoo14-addon-l10n_et_hr_employee_wizard
Version: 14.0.1.0.1.dev1
Summary: Ethiopian localization of new employee wizard
Home-page: https://github.com/trevi-software/trevi-hr
Author: TREVI Software, Michael Telahun Makonnen
License: AGPL-3
Classifier: Programming Language :: Python
Classifier: Framework :: Odoo
Classifier: Framework :: Odoo :: 14.0
Classifier: License :: OSI Approved :: GNU Affero General Public License v3
Requires-Python: >=3.6
Requires-Dist: odoo14-addon-ethiopic-calendar
Requires-Dist: odoo14-addon-hr-employee-wizard
Requires-Dist: odoo14-addon-l10n-et-hr
Requires-Dist: odoo<14.1dev,>=14.0a
